recipe_md/__init__.py
recipe_md/cli.py
recipe_md/recipe_md.py
recipe_md/utils.py
recipe_md-0.1.0.dist-info/entry_points.txt
recipe_md-0.1.0.dist-info/LICENSE
recipe_md-0.1.0.dist-info/WHEEL
recipe_md-0.1.0.dist-info/METADATA
recipe_md-0.1.0.dist-info/RECORD
