Metadata-Version: 2.1
Name: recipe-md
Version: 0.1.0
Summary: Scrape and convert recipes to markdown
License: MIT
Author: rafa
Author-email: rafapi@gmail.com
Requires-Python: >=3.7,<4.0
Classifier: License :: OSI Approved :: MIT License
Classifier: Programming Language :: Python :: 3
Classifier: Programming Language :: Python :: 3.7
Classifier: Programming Language :: Python :: 3.8
Requires-Dist: Pillow (>=7.2.0,<8.0.0)
Requires-Dist: flake8 (>=3.8.3,<4.0.0)
Requires-Dist: python-slugify (>=4.0.1,<5.0.0)
Requires-Dist: recipe-scrapers (>=8.0.1,<9.0.0)
Requires-Dist: requests (>=2.24.0,<3.0.0)
Requires-Dist: typer (>=0.3.0,<0.4.0)
